{"eval0": [{"player": 522, "dealer": 478}, {"player": 783, "dealer": 217}, {"player": 508, "dealer": 492}, {"player": 0, "dealer": 1000}], "eval1": [{"player": 510, "dealer": 490}, {"player": 737, "dealer": 263}, {"player": 454, "dealer": 546}, {"player": 0, "dealer": 1000}], "eval2": [{"player": 500, "dealer": 500}, {"player": 739, "dealer": 261}, {"player": 498, "dealer": 502}, {"player": 0, "dealer": 1000}], "eval3": [{"player": 491, "dealer": 509}, {"player": 739, "dealer": 261}, {"player": 496, "dealer": 504}, {"player": 0, "dealer": 1000}], "eval4": [{"player": 506, "dealer": 494}, {"player": 744, "dealer": 256}, {"player": 503, "dealer": 497}, {"player": 0, "dealer": 1000}], "eval5": [{"player": 517, "dealer": 483}, {"player": 772, "dealer": 228}, {"player": 492, "dealer": 508}, {"player": 0, "dealer": 1000}], "eval6": [{"player": 508, "dealer": 492}, {"player": 745, "dealer": 255}, {"player": 509, "dealer": 491}, {"player": 0, "dealer": 1000}], "eval7": [{"player": 471, "dealer": 529}, {"player": 749, "dealer": 251}, {"player": 531, "dealer": 469}, {"player": 0, "dealer": 1000}], "eval8": [{"player": 477, "dealer": 523}, {"player": 743, "dealer": 257}, {"player": 517, "dealer": 483}, {"player": 0, "dealer": 1000}], "eval9": [{"player": 478, "dealer": 522}, {"player": 767, "dealer": 233}, {"player": 495, "dealer": 505}, {"player": 0, "dealer": 1000}], "eval10": [{"player": 502, "dealer": 498}, {"player": 771, "dealer": 229}, {"player": 502, "dealer": 498}, {"player": 0, "dealer": 1000}], "eval11": [{"player": 505, "dealer": 495}, {"player": 757, "dealer": 243}, {"player": 482, "dealer": 518}, {"player": 0, "dealer": 1000}], "eval12": [{"player": 516, "dealer": 484}, {"player": 731, "dealer": 269}, {"player": 515, "dealer": 485}, {"player": 0, "dealer": 1000}], "eval13": [{"player": 489, "dealer": 511}, {"player": 743, "dealer": 257}, {"player": 500, "dealer": 500}, {"player": 0, "dealer": 1000}], "eval14": [{"player": 492, "dealer": 508}, {"player": 736, "dealer": 264}, {"player": 476, "dealer": 524}, {"player": 0, "dealer": 1000}], "eval15": [{"player": 488, "dealer": 512}, {"player": 737, "dealer": 263}, {"player": 488, "dealer": 512}, {"player": 0, "dealer": 1000}], "eval16": [{"player": 494, "dealer": 506}, {"player": 773, "dealer": 227}, {"player": 503, "dealer": 497}, {"player": 0, "dealer": 1000}], "eval17": [{"player": 510, "dealer": 490}, {"player": 730, "dealer": 270}, {"player": 495, "dealer": 505}, {"player": 0, "dealer": 1000}], "eval18": [{"player": 489, "dealer": 511}, {"player": 759, "dealer": 241}, {"player": 492, "dealer": 508}, {"player": 0, "dealer": 1000}], "eval19": [{"player": 500, "dealer": 500}, {"player": 751, "dealer": 249}, {"player": 496, "dealer": 504}, {"player": 0, "dealer": 1000}], "eval20": [{"player": 495, "dealer": 505}, {"player": 756, "dealer": 244}, {"player": 500, "dealer": 500}, {"player": 0, "dealer": 1000}], "eval21": [{"player": 461, "dealer": 539}, {"player": 759, "dealer": 241}, {"player": 501, "dealer": 499}, {"player": 0, "dealer": 1000}], "eval22": [{"player": 485, "dealer": 515}, {"player": 762, "dealer": 238}, {"player": 509, "dealer": 491}, {"player": 0, "dealer": 1000}], "eval23": [{"player": 504, "dealer": 496}, {"player": 741, "dealer": 259}, {"player": 494, "dealer": 506}, {"player": 0, "dealer": 1000}], "eval24": [{"player": 502, "dealer": 498}, {"player": 750, "dealer": 250}, {"player": 519, "dealer": 481}, {"player": 0, "dealer": 1000}], "eval25": [{"player": 506, "dealer": 494}, {"player": 744, "dealer": 256}, {"player": 513, "dealer": 487}, {"player": 0, "dealer": 1000}], "eval26": [{"player": 501, "dealer": 499}, {"player": 752, "dealer": 248}, {"player": 489, "dealer": 511}, {"player": 0, "dealer": 1000}], "eval27": [{"player": 487, "dealer": 513}, {"player": 757, "dealer": 243}, {"player": 508, "dealer": 492}, {"player": 0, "dealer": 1000}], "eval28": [{"player": 518, "dealer": 482}, {"player": 745, "dealer": 255}, {"player": 524, "dealer": 476}, {"player": 0, "dealer": 1000}], "eval29": [{"player": 493, "dealer": 507}, {"player": 755, "dealer": 245}, {"player": 503, "dealer": 497}, {"player": 0, "dealer": 1000}], "eval30": [{"player": 502, "dealer": 498}, {"player": 761, "dealer": 239}, {"player": 491, "dealer": 509}, {"player": 0, "dealer": 1000}], "eval31": [{"player": 479, "dealer": 521}, {"player": 765, "dealer": 235}, {"player": 458, "dealer": 542}, {"player": 0, "dealer": 1000}], "eval32": [{"player": 490, "dealer": 510}, {"player": 769, "dealer": 231}, {"player": 482, "dealer": 518}, {"player": 0, "dealer": 1000}], "eval33": [{"player": 502, "dealer": 498}, {"player": 741, "dealer": 259}, {"player": 468, "dealer": 532}, {"player": 0, "dealer": 1000}], "eval34": [{"player": 487, "dealer": 513}, {"player": 764, "dealer": 236}, {"player": 523, "dealer": 477}, {"player": 0, "dealer": 1000}], "eval35": [{"player": 490, "dealer": 510}, {"player": 737, "dealer": 263}, {"player": 502, "dealer": 498}, {"player": 0, "dealer": 1000}], "eval36": [{"player": 502, "dealer": 498}, {"player": 766, "dealer": 234}, {"player": 485, "dealer": 515}, {"player": 0, "dealer": 1000}], "eval37": [{"player": 478, "dealer": 522}, {"player": 749, "dealer": 251}, {"player": 505, "dealer": 495}, {"player": 0, "dealer": 1000}], "eval38": [{"player": 491, "dealer": 509}, {"player": 735, "dealer": 265}, {"player": 489, "dealer": 511}, {"player": 0, "dealer": 1000}], "eval39": [{"player": 528, "dealer": 472}, {"player": 768, "dealer": 232}, {"player": 490, "dealer": 510}, {"player": 0, "dealer": 1000}], "eval40": [{"player": 453, "dealer": 547}, {"player": 782, "dealer": 218}, {"player": 502, "dealer": 498}, {"player": 0, "dealer": 1000}], "eval41": [{"player": 511, "dealer": 489}, {"player": 718, "dealer": 282}, {"player": 494, "dealer": 506}, {"player": 0, "dealer": 1000}], "eval42": [{"player": 482, "dealer": 518}, {"player": 760, "dealer": 240}, {"player": 508, "dealer": 492}, {"player": 0, "dealer": 1000}], "eval43": [{"player": 495, "dealer": 505}, {"player": 716, "dealer": 284}, {"player": 495, "dealer": 505}, {"player": 0, "dealer": 1000}], "eval44": [{"player": 511, "dealer": 489}, {"player": 757, "dealer": 243}, {"player": 510, "dealer": 490}, {"player": 0, "dealer": 1000}], "eval45": [{"player": 521, "dealer": 479}, {"player": 737, "dealer": 263}, {"player": 516, "dealer": 484}, {"player": 0, "dealer": 1000}], "eval46": [{"player": 511, "dealer": 489}, {"player": 769, "dealer": 231}, {"player": 522, "dealer": 478}, {"player": 0, "dealer": 1000}], "eval47": [{"player": 519, "dealer": 481}, {"player": 748, "dealer": 252}, {"player": 492, "dealer": 508}, {"player": 0, "dealer": 1000}], "eval48": [{"player": 503, "dealer": 497}, {"player": 749, "dealer": 251}, {"player": 484, "dealer": 516}, {"player": 0, "dealer": 1000}], "eval49": [{"player": 470, "dealer": 530}, {"player": 761, "dealer": 239}, {"player": 505, "dealer": 495}, {"player": 0, "dealer": 1000}], "eval50": [{"player": 492, "dealer": 508}, {"player": 758, "dealer": 242}, {"player": 493, "dealer": 507}, {"player": 0, "dealer": 1000}], "eval51": [{"player": 507, "dealer": 493}, {"player": 731, "dealer": 269}, {"player": 515, "dealer": 485}, {"player": 0, "dealer": 1000}], "eval52": [{"player": 501, "dealer": 499}, {"player": 748, "dealer": 252}, {"player": 508, "dealer": 492}, {"player": 0, "dealer": 1000}], "eval53": [{"player": 493, "dealer": 507}, {"player": 766, "dealer": 234}, {"player": 479, "dealer": 521}, {"player": 0, "dealer": 1000}], "eval54": [{"player": 541, "dealer": 459}, {"player": 759, "dealer": 241}, {"player": 488, "dealer": 512}, {"player": 0, "dealer": 1000}], "eval55": [{"player": 481, "dealer": 519}, {"player": 747, "dealer": 253}, {"player": 505, "dealer": 495}, {"player": 0, "dealer": 1000}], "eval56": [{"player": 503, "dealer": 497}, {"player": 754, "dealer": 246}, {"player": 510, "dealer": 490}, {"player": 0, "dealer": 1000}], "eval57": [{"player": 504, "dealer": 496}, {"player": 733, "dealer": 267}, {"player": 479, "dealer": 521}, {"player": 0, "dealer": 1000}], "eval58": [{"player": 470, "dealer": 530}, {"player": 757, "dealer": 243}, {"player": 515, "dealer": 485}, {"player": 0, "dealer": 1000}], "eval59": [{"player": 492, "dealer": 508}, {"player": 769, "dealer": 231}, {"player": 458, "dealer": 542}, {"player": 0, "dealer": 1000}], "eval60": [{"player": 481, "dealer": 519}, {"player": 742, "dealer": 258}, {"player": 506, "dealer": 494}, {"player": 0, "dealer": 1000}], "eval61": [{"player": 469, "dealer": 531}, {"player": 755, "dealer": 245}, {"player": 544, "dealer": 456}, {"player": 0, "dealer": 1000}], "eval62": [{"player": 489, "dealer": 511}, {"player": 738, "dealer": 262}, {"player": 500, "dealer": 500}, {"player": 0, "dealer": 1000}], "eval63": [{"player": 502, "dealer": 498}, {"player": 756, "dealer": 244}, {"player": 481, "dealer": 519}, {"player": 0, "dealer": 1000}], "eval64": [{"player": 476, "dealer": 524}, {"player": 787, "dealer": 213}, {"player": 520, "dealer": 480}, {"player": 0, "dealer": 1000}], "eval65": [{"player": 498, "dealer": 502}, {"player": 754, "dealer": 246}, {"player": 483, "dealer": 517}, {"player": 0, "dealer": 1000}], "eval66": [{"player": 515, "dealer": 485}, {"player": 739, "dealer": 261}, {"player": 480, "dealer": 520}, {"player": 0, "dealer": 1000}], "eval67": [{"player": 506, "dealer": 494}, {"player": 747, "dealer": 253}, {"player": 506, "dealer": 494}, {"player": 0, "dealer": 1000}], "eval68": [{"player": 518, "dealer": 482}, {"player": 744, "dealer": 256}, {"player": 503, "dealer": 497}, {"player": 0, "dealer": 1000}], "eval69": [{"player": 507, "dealer": 493}, {"player": 763, "dealer": 237}, {"player": 480, "dealer": 520}, {"player": 0, "dealer": 1000}], "eval70": [{"player": 463, "dealer": 537}, {"player": 743, "dealer": 257}, {"player": 521, "dealer": 479}, {"player": 0, "dealer": 1000}], "eval71": [{"player": 501, "dealer": 499}, {"player": 770, "dealer": 230}, {"player": 523, "dealer": 477}, {"player": 0, "dealer": 1000}], "eval72": [{"player": 510, "dealer": 490}, {"player": 751, "dealer": 249}, {"player": 497, "dealer": 503}, {"player": 0, "dealer": 1000}], "eval73": [{"player": 496, "dealer": 504}, {"player": 759, "dealer": 241}, {"player": 513, "dealer": 487}, {"player": 0, "dealer": 1000}], "eval74": [{"player": 492, "dealer": 508}, {"player": 748, "dealer": 252}, {"player": 505, "dealer": 495}, {"player": 0, "dealer": 1000}], "eval75": [{"player": 485, "dealer": 515}, {"player": 759, "dealer": 241}, {"player": 505, "dealer": 495}, {"player": 0, "dealer": 1000}], "eval76": [{"player": 505, "dealer": 495}, {"player": 740, "dealer": 260}, {"player": 521, "dealer": 479}, {"player": 0, "dealer": 1000}], "eval77": [{"player": 517, "dealer": 483}, {"player": 760, "dealer": 240}, {"player": 503, "dealer": 497}, {"player": 0, "dealer": 1000}], "eval78": [{"player": 487, "dealer": 513}, {"player": 750, "dealer": 250}, {"player": 491, "dealer": 509}, {"player": 0, "dealer": 1000}], "eval79": [{"player": 479, "dealer": 521}, {"player": 750, "dealer": 250}, {"player": 497, "dealer": 503}, {"player": 0, "dealer": 1000}], "eval80": [{"player": 498, "dealer": 502}, {"player": 768, "dealer": 232}, {"player": 499, "dealer": 501}, {"player": 0, "dealer": 1000}], "eval81": [{"player": 492, "dealer": 508}, {"player": 741, "dealer": 259}, {"player": 504, "dealer": 496}, {"player": 0, "dealer": 1000}], "eval82": [{"player": 490, "dealer": 510}, {"player": 730, "dealer": 270}, {"player": 491, "dealer": 509}, {"player": 0, "dealer": 1000}], "eval83": [{"player": 500, "dealer": 500}, {"player": 762, "dealer": 238}, {"player": 487, "dealer": 513}, {"player": 0, "dealer": 1000}], "eval84": [{"player": 509, "dealer": 491}, {"player": 759, "dealer": 241}, {"player": 512, "dealer": 488}, {"player": 0, "dealer": 1000}], "eval85": [{"player": 488, "dealer": 512}, {"player": 745, "dealer": 255}, {"player": 481, "dealer": 519}, {"player": 0, "dealer": 1000}], "eval86": [{"player": 524, "dealer": 476}, {"player": 760, "dealer": 240}, {"player": 496, "dealer": 504}, {"player": 0, "dealer": 1000}], "eval87": [{"player": 511, "dealer": 489}, {"player": 768, "dealer": 232}, {"player": 494, "dealer": 506}, {"player": 0, "dealer": 1000}], "eval88": [{"player": 524, "dealer": 476}, {"player": 742, "dealer": 258}, {"player": 481, "dealer": 519}, {"player": 0, "dealer": 1000}], "eval89": [{"player": 497, "dealer": 503}, {"player": 770, "dealer": 230}, {"player": 482, "dealer": 518}, {"player": 0, "dealer": 1000}], "eval90": [{"player": 464, "dealer": 536}, {"player": 742, "dealer": 258}, {"player": 496, "dealer": 504}, {"player": 0, "dealer": 1000}], "eval91": [{"player": 499, "dealer": 501}, {"player": 727, "dealer": 273}, {"player": 509, "dealer": 491}, {"player": 0, "dealer": 1000}], "eval92": [{"player": 491, "dealer": 509}, {"player": 739, "dealer": 261}, {"player": 509, "dealer": 491}, {"player": 0, "dealer": 1000}], "eval93": [{"player": 491, "dealer": 509}, {"player": 721, "dealer": 279}, {"player": 490, "dealer": 510}, {"player": 0, "dealer": 1000}], "eval94": [{"player": 516, "dealer": 484}, {"player": 739, "dealer": 261}, {"player": 483, "dealer": 517}, {"player": 0, "dealer": 1000}], "eval95": [{"player": 508, "dealer": 492}, {"player": 740, "dealer": 260}, {"player": 507, "dealer": 493}, {"player": 0, "dealer": 1000}], "eval96": [{"player": 471, "dealer": 529}, {"player": 777, "dealer": 223}, {"player": 507, "dealer": 493}, {"player": 0, "dealer": 1000}], "eval97": [{"player": 492, "dealer": 508}, {"player": 741, "dealer": 259}, {"player": 513, "dealer": 487}, {"player": 0, "dealer": 1000}], "eval98": [{"player": 496, "dealer": 504}, {"player": 747, "dealer": 253}, {"player": 496, "dealer": 504}, {"player": 0, "dealer": 1000}], "eval99": [{"player": 480, "dealer": 520}, {"player": 752, "dealer": 248}, {"player": 505, "dealer": 495}, {"player": 0, "dealer": 1000}]}